crypto_price_mcp/__init__.py
crypto_price_mcp/__main__.py
crypto_price_mcp/crypto_mcp.py
crypto_price_mcp-0.1.0.dist-info/licenses/LICENSE
crypto_price_mcp-0.1.0.dist-info/METADATA
crypto_price_mcp-0.1.0.dist-info/WHEEL
crypto_price_mcp-0.1.0.dist-info/entry_points.txt
crypto_price_mcp-0.1.0.dist-info/top_level.txt
crypto_price_mcp-0.1.0.dist-info/RECORD
